[
    {"nombre": "Super Mario Bros. La película", "precio": 3.50},
    {"nombre": "The Batman", "precio": 3.00},
    {"nombre": "Spider-Man: No Way Home", "precio": 3.75},
    {"nombre": "Doctor Strange en el Multiverso de la Locura", "precio": 3.00},
    {"nombre": "Fast and Furious X", "precio": 3.50},
    {"nombre": "The Marvels", "precio": 3.00},
    {"nombre": "Black Widow", "precio": 3.75},
    {"nombre": "The Flash", "precio": 3.25},
    {"nombre": "Oppenheimer ", "precio": 3.00},
    {"nombre": "Sonic 2: La película", "precio": 3.25}
  ]
  